MANIFEST.in
VERSION
requirements.txt
setup.py
aorta/__init__.py
aorta/basemessage.py
aorta/command.py
aorta/commandhandler.py
aorta/commandhandlermetaclass.py
aorta/event.py
aorta/eventlistener.py
aorta/eventlistenermetaclass.py
aorta/exceptions.py
aorta/ipublisher.py
aorta/messagefielddescriptor.py
aorta/messagehandler.py
aorta/messagehandlermetaclass.py
aorta/messagehandlersprovider.py
aorta/messagemetaclass.py
aorta/messageobjectdescriptor.py
aorta/messageoptions.py
aorta/messagepublisher.py
aorta/package.json
aorta/sender.py
aorta.egg-info/PKG-INFO
aorta.egg-info/SOURCES.txt
aorta.egg-info/dependency_links.txt
aorta.egg-info/requires.txt
aorta.egg-info/top_level.txt
aorta/handlers/__init__.py
aorta/handlers/ping.py
aorta/models/__init__.py
aorta/models/message.py
aorta/models/messageheader.py
aorta/models/messagemetadata.py
aorta/models/google/__init__.py
aorta/models/google/messagepublished.py
aorta/models/google/pubsubmessage.py
aorta/tests/__init__.py
aorta/tests/conftest.py
aorta/tests/test_integration_command_handler_match.py
aorta/tests/test_integration_noop.py
aorta/tests/test_integration_publish.py
aorta/tests/test_system_noop.py
aorta/tests/test_unit_messagehandlerprovider.py
aorta/tests/test_unit_messageheader.py
aorta/tests/test_unit_multimessage.py
aorta/tests/test_unit_noop.py
aorta/tests/pydantic/__init__.py
aorta/tests/pydantic/conftest.py
aorta/tests/pydantic/test_unit_validation.py
aorta/transport/__init__.py
aorta/transport/google.py
aorta/transport/http.py
aorta/transport/itransport.py
aorta/transport/null.py
aorta/types/__init__.py
aorta/types/retrycommand.py
examples/google-pubsub.py
examples/http-receiver.py